drfutils/__init__.py
drfutils/admin.py
drfutils/conf.py
drfutils/decorators.py
drfutils/fields.py
drfutils/models.py
drfutils/permissions.py
drfutils/serializers.py
drfutils/migrations/0001_initial.py
drfutils/migrations/__init__.py
drf_utils-0.3.0.dist-info/METADATA
drf_utils-0.3.0.dist-info/WHEEL
drf_utils-0.3.0.dist-info/top_level.txt
drf_utils-0.3.0.dist-info/RECORD
