Metadata-Version: 2.1
Name: drf-utils
Version: 0.3.0
Summary: Reusable utilities for DRF used at Ployst
Home-page: https://github.com/ployst/drf-utils
Author: The ployst team
Author-email: dev@ployst.com
License: UNKNOWN
Platform: UNKNOWN
Classifier: Environment :: Console
Classifier: Intended Audience :: Developers
Classifier: Programming Language :: Python
Classifier: Programming Language :: Python :: 2
Classifier: Programming Language :: Python :: 2.7
Classifier: Programming Language :: Python :: 3
Classifier: Programming Language :: Python :: 3.2
Classifier: Programming Language :: Python :: 3.3
Classifier: Programming Language :: Python :: 3.4
Classifier: Topic :: Software Development :: Libraries
